{
  "brands": [
    {
      "name": "BlackMarray",
      "date": "Tue Jan 19 2021 23:07:16 GMT+0800 (中国标准时间)",
      "id": 6
    },
    {
      "name": "Google",
      "date": "Tue Jan 19 2021 23:44:16 GMT+0800 (中国标准时间)",
      "id": 7
    },
    {
      "name": "TCL",
      "date": "Tue Jan 19 2021 23:06:16 GMT+0800 (中国标准时间)",
      "id": 8
    },
    {
      "name": "TCL",
      "date": "Tue Jan 19 2021 23:49:16 GMT+0800 (中国标准时间)",
      "id": 9
    },
    {
      "name": "csk",
      "date": "2021-1-30",
      "id": 10
    },
    {
      "name": "abcd",
      "date": "2021-01-20T13:24:03.606Z",
      "id": 12
    },
    {
      "name": "sss",
      "date": "2021-01-20T15:07:44.349Z",
      "id": 13
    }
  ]
}