{
  "users": [
    {
      "id": 1,
      "name": "张三",
      "age": 18,
      "gender": "男"
    },
    {
      "id": 2,
      "name": "临漳",
      "age": 18,
      "gender": "男"
    },
    {
      "id": 3,
      "name": "王宏",
      "age": 18,
      "gender": "男"
    },
    {
      "id": 8,
      "name": "关羽",
      "age": 18,
      "gender": "男"
    },
    {
      "name": "曹操",
      "age": "18",
      "gender": "男",
      "id": 20
    },
    {
      "name": "张飞",
      "gender": "男",
      "age": "27",
      "id": 21
    },
    {
      "name": "承苏凯",
      "gender": "男",
      "age": "25",
      "id": 22
    }
  ]
}